brewse/__init__.py
brewse/cli.py
brewse-0.2.1.dist-info/METADATA
brewse-0.2.1.dist-info/WHEEL
brewse-0.2.1.dist-info/entry_points.txt
brewse-0.2.1.dist-info/licenses/LICENSE
brewse-0.2.1.dist-info/RECORD
