Metadata-Version: 2.4
Name: brewse
Version: 0.2.1
Summary: An interactive TUI browser for Homebrew packages
License-Expression: MIT
License-File: LICENSE
Requires-Python: >=3.7
Requires-Dist: windows-curses; platform_system == 'Windows'
